pdflayers/__init__.py
pdflayers/__main__.py
pdflayers/utils.py
pdflayers-0.2.1.dist-info/LICENSE
pdflayers-0.2.1.dist-info/METADATA
pdflayers-0.2.1.dist-info/WHEEL
pdflayers-0.2.1.dist-info/entry_points.txt
pdflayers-0.2.1.dist-info/top_level.txt
pdflayers-0.2.1.dist-info/RECORD
