Metadata-Version: 2.1
Name: pdflayers
Version: 0.2.1
Summary: PDF layer handling.
Home-page: https://github.com/SimonSegerblomRex/pdflayers
Author: Simon Segerblom Rex
License: MIT
Classifier: Development Status :: 3 - Alpha
Classifier: Intended Audience :: Developers
Classifier: License :: OSI Approved :: MIT License
Classifier: Programming Language :: Python
Classifier: Programming Language :: Python :: 3.5
Classifier: Programming Language :: Python :: 3.6
Classifier: Programming Language :: Python :: 3.7
Classifier: Programming Language :: Python :: 3 :: Only
Requires-Python: >=3.5
License-File: LICENSE
Requires-Dist: pikepdf
